{
  "series_id": "PCEPILFE",
  "name": "Core PCE 核心個人消費支出物價指數",
  "name_en": "Core PCE Price Index",
  "category": "inflation",
  "unit": "% YoY",
  "raw_unit": "Index",
  "frequency": "monthly",
  "transform": "yoy",
  "source": "BEA via FRED",
  "raw_observations": [
    {
      "date": "1959-01-01",
      "value": 15.501
    },
    {
      "date": "1959-02-01",
      "value": 15.513
    },
    {
      "date": "1959-03-01",
      "value": 15.531
    },
    {
      "date": "1959-04-01",
      "value": 15.57
    },
    {
      "date": "1959-05-01",
      "value": 15.589
    },
    {
      "date": "1959-06-01",
      "value": 15.635
    },
    {
      "date": "1959-07-01",
      "value": 15.672
    },
    {
      "date": "1959-08-01",
      "value": 15.697
    },
    {
      "date": "1959-09-01",
      "value": 15.738
    },
    {
      "date": "1959-10-01",
      "value": 15.765
    },
    {
      "date": "1959-11-01",
      "value": 15.794
    },
    {
      "date": "1959-12-01",
      "value": 15.818
    },
    {
      "date": "1960-01-01",
      "value": 15.822
    },
    {
      "date": "1960-02-01",
      "value": 15.852
    },
    {
      "date": "1960-03-01",
      "value": 15.853
    },
    {
      "date": "1960-04-01",
      "value": 15.882
    },
    {
      "date": "1960-05-01",
      "value": 15.908
    },
    {
      "date": "1960-06-01",
      "value": 15.917
    },
    {
      "date": "1960-07-01",
      "value": 15.945
    },
    {
      "date": "1960-08-01",
      "value": 15.968
    },
    {
      "date": "1960-09-01",
      "value": 15.981
    },
    {
      "date": "1960-10-01",
      "value": 15.99
    },
    {
      "date": "1960-11-01",
      "value": 16.033
    },
    {
      "date": "1960-12-01",
      "value": 16.028
    },
    {
      "date": "1961-01-01",
      "value": 16.032
    },
    {
      "date": "1961-02-01",
      "value": 16.048
    },
    {
      "date": "1961-03-01",
      "value": 16.053
    },
    {
      "date": "1961-04-01",
      "value": 16.075
    },
    {
      "date": "1961-05-01",
      "value": 16.096
    },
    {
      "date": "1961-06-01",
      "value": 16.12
    },
    {
      "date": "1961-07-01",
      "value": 16.145
    },
    {
      "date": "1961-08-01",
      "value": 16.162
    },
    {
      "date": "1961-09-01",
      "value": 16.194
    },
    {
      "date": "1961-10-01",
      "value": 16.199
    },
    {
      "date": "1961-11-01",
      "value": 16.202
    },
    {
      "date": "1961-12-01",
      "value": 16.216
    },
    {
      "date": "1962-01-01",
      "value": 16.235
    },
    {
      "date": "1962-02-01",
      "value": 16.262
    },
    {
      "date": "1962-03-01",
      "value": 16.3
    },
    {
      "date": "1962-04-01",
      "value": 16.303
    },
    {
      "date": "1962-05-01",
      "value": 16.326
    },
    {
      "date": "1962-06-01",
      "value": 16.356
    },
    {
      "date": "1962-07-01",
      "value": 16.37
    },
    {
      "date": "1962-08-01",
      "value": 16.372
    },
    {
      "date": "1962-09-01",
      "value": 16.404
    },
    {
      "date": "1962-10-01",
      "value": 16.403
    },
    {
      "date": "1962-11-01",
      "value": 16.415
    },
    {
      "date": "1962-12-01",
      "value": 16.42
    },
    {
      "date": "1963-01-01",
      "value": 16.451
    },
    {
      "date": "1963-02-01",
      "value": 16.47
    },
    {
      "date": "1963-03-01",
      "value": 16.48
    },
    {
      "date": "1963-04-01",
      "value": 16.5
    },
    {
      "date": "1963-05-01",
      "value": 16.53
    },
    {
      "date": "1963-06-01",
      "value": 16.558
    },
    {
      "date": "1963-07-01",
      "value": 16.573
    },
    {
      "date": "1963-08-01",
      "value": 16.588
    },
    {
      "date": "1963-09-01",
      "value": 16.618
    },
    {
      "date": "1963-10-01",
      "value": 16.655
    },
    {
      "date": "1963-11-01",
      "value": 16.67
    },
    {
      "date": "1963-12-01",
      "value": 16.694
    },
    {
      "date": "1964-01-01",
      "value": 16.717
    },
    {
      "date": "1964-02-01",
      "value": 16.749
    },
    {
      "date": "1964-03-01",
      "value": 16.765
    },
    {
      "date": "1964-04-01",
      "value": 16.78
    },
    {
      "date": "1964-05-01",
      "value": 16.794
    },
    {
      "date": "1964-06-01",
      "value": 16.806
    },
    {
      "date": "1964-07-01",
      "value": 16.823
    },
    {
      "date": "1964-08-01",
      "value": 16.845
    },
    {
      "date": "1964-09-01",
      "value": 16.852
    },
    {
      "date": "1964-10-01",
      "value": 16.859
    },
    {
      "date": "1964-11-01",
      "value": 16.883
    },
    {
      "date": "1964-12-01",
      "value": 16.907
    },
    {
      "date": "1965-01-01",
      "value": 16.93
    },
    {
      "date": "1965-02-01",
      "value": 16.95
    },
    {
      "date": "1965-03-01",
      "value": 16.96
    },
    {
      "date": "1965-04-01",
      "value": 16.98
    },
    {
      "date": "1965-05-01",
      "value": 17.011
    },
    {
      "date": "1965-06-01",
      "value": 17.007
    },
    {
      "date": "1965-07-01",
      "value": 17.024
    },
    {
      "date": "1965-08-01",
      "value": 17.056
    },
    {
      "date": "1965-09-01",
      "value": 17.076
    },
    {
      "date": "1965-10-01",
      "value": 17.07
    },
    {
      "date": "1965-11-01",
      "value": 17.102
    },
    {
      "date": "1965-12-01",
      "value": 17.154
    },
    {
      "date": "1966-01-01",
      "value": 17.159
    },
    {
      "date": "1966-02-01",
      "value": 17.201
    },
    {
      "date": "1966-03-01",
      "value": 17.223
    },
    {
      "date": "1966-04-01",
      "value": 17.285
    },
    {
      "date": "1966-05-01",
      "value": 17.331
    },
    {
      "date": "1966-06-01",
      "value": 17.387
    },
    {
      "date": "1966-07-01",
      "value": 17.438
    },
    {
      "date": "1966-08-01",
      "value": 17.47
    },
    {
      "date": "1966-09-01",
      "value": 17.524
    },
    {
      "date": "1966-10-01",
      "value": 17.581
    },
    {
      "date": "1966-11-01",
      "value": 17.625
    },
    {
      "date": "1966-12-01",
      "value": 17.679
    },
    {
      "date": "1967-01-01",
      "value": 17.695
    },
    {
      "date": "1967-02-01",
      "value": 17.727
    },
    {
      "date": "1967-03-01",
      "value": 17.754
    },
    {
      "date": "1967-04-01",
      "value": 17.803
    },
    {
      "date": "1967-05-01",
      "value": 17.842
    },
    {
      "date": "1967-06-01",
      "value": 17.887
    },
    {
      "date": "1967-07-01",
      "value": 17.948
    },
    {
      "date": "1967-08-01",
      "value": 18.003
    },
    {
      "date": "1967-09-01",
      "value": 18.067
    },
    {
      "date": "1967-10-01",
      "value": 18.134
    },
    {
      "date": "1967-11-01",
      "value": 18.192
    },
    {
      "date": "1967-12-01",
      "value": 18.237
    },
    {
      "date": "1968-01-01",
      "value": 18.318
    },
    {
      "date": "1968-02-01",
      "value": 18.397
    },
    {
      "date": "1968-03-01",
      "value": 18.47
    },
    {
      "date": "1968-04-01",
      "value": 18.538
    },
    {
      "date": "1968-05-01",
      "value": 18.608
    },
    {
      "date": "1968-06-01",
      "value": 18.681
    },
    {
      "date": "1968-07-01",
      "value": 18.743
    },
    {
      "date": "1968-08-01",
      "value": 18.816
    },
    {
      "date": "1968-09-01",
      "value": 18.892
    },
    {
      "date": "1968-10-01",
      "value": 18.969
    },
    {
      "date": "1968-11-01",
      "value": 19.041
    },
    {
      "date": "1968-12-01",
      "value": 19.098
    },
    {
      "date": "1969-01-01",
      "value": 19.17
    },
    {
      "date": "1969-02-01",
      "value": 19.236
    },
    {
      "date": "1969-03-01",
      "value": 19.326
    },
    {
      "date": "1969-04-01",
      "value": 19.4
    },
    {
      "date": "1969-05-01",
      "value": 19.478
    },
    {
      "date": "1969-06-01",
      "value": 19.545
    },
    {
      "date": "1969-07-01",
      "value": 19.636
    },
    {
      "date": "1969-08-01",
      "value": 19.691
    },
    {
      "date": "1969-09-01",
      "value": 19.77
    },
    {
      "date": "1969-10-01",
      "value": 19.855
    },
    {
      "date": "1969-11-01",
      "value": 19.931
    },
    {
      "date": "1969-12-01",
      "value": 20.005
    }
  ],
  "latest_raw_date": "1969-12-01",
  "latest_raw_value": 20.005,
  "yoy_observations": [
    {
      "date": "1960-01-01",
      "value": 2.071
    },
    {
      "date": "1960-02-01",
      "value": 2.185
    },
    {
      "date": "1960-03-01",
      "value": 2.073
    },
    {
      "date": "1960-04-01",
      "value": 2.004
    },
    {
      "date": "1960-05-01",
      "value": 2.046
    },
    {
      "date": "1960-06-01",
      "value": 1.804
    },
    {
      "date": "1960-07-01",
      "value": 1.742
    },
    {
      "date": "1960-08-01",
      "value": 1.726
    },
    {
      "date": "1960-09-01",
      "value": 1.544
    },
    {
      "date": "1960-10-01",
      "value": 1.427
    },
    {
      "date": "1960-11-01",
      "value": 1.513
    },
    {
      "date": "1960-12-01",
      "value": 1.328
    },
    {
      "date": "1961-01-01",
      "value": 1.327
    },
    {
      "date": "1961-02-01",
      "value": 1.236
    },
    {
      "date": "1961-03-01",
      "value": 1.262
    },
    {
      "date": "1961-04-01",
      "value": 1.215
    },
    {
      "date": "1961-05-01",
      "value": 1.182
    },
    {
      "date": "1961-06-01",
      "value": 1.275
    },
    {
      "date": "1961-07-01",
      "value": 1.254
    },
    {
      "date": "1961-08-01",
      "value": 1.215
    },
    {
      "date": "1961-09-01",
      "value": 1.333
    },
    {
      "date": "1961-10-01",
      "value": 1.307
    },
    {
      "date": "1961-11-01",
      "value": 1.054
    },
    {
      "date": "1961-12-01",
      "value": 1.173
    },
    {
      "date": "1962-01-01",
      "value": 1.266
    },
    {
      "date": "1962-02-01",
      "value": 1.333
    },
    {
      "date": "1962-03-01",
      "value": 1.539
    },
    {
      "date": "1962-04-01",
      "value": 1.418
    },
    {
      "date": "1962-05-01",
      "value": 1.429
    },
    {
      "date": "1962-06-01",
      "value": 1.464
    },
    {
      "date": "1962-07-01",
      "value": 1.394
    },
    {
      "date": "1962-08-01",
      "value": 1.299
    },
    {
      "date": "1962-09-01",
      "value": 1.297
    },
    {
      "date": "1962-10-01",
      "value": 1.259
    },
    {
      "date": "1962-11-01",
      "value": 1.315
    },
    {
      "date": "1962-12-01",
      "value": 1.258
    },
    {
      "date": "1963-01-01",
      "value": 1.33
    },
    {
      "date": "1963-02-01",
      "value": 1.279
    },
    {
      "date": "1963-03-01",
      "value": 1.104
    },
    {
      "date": "1963-04-01",
      "value": 1.208
    },
    {
      "date": "1963-05-01",
      "value": 1.25
    },
    {
      "date": "1963-06-01",
      "value": 1.235
    },
    {
      "date": "1963-07-01",
      "value": 1.24
    },
    {
      "date": "1963-08-01",
      "value": 1.319
    },
    {
      "date": "1963-09-01",
      "value": 1.305
    },
    {
      "date": "1963-10-01",
      "value": 1.536
    },
    {
      "date": "1963-11-01",
      "value": 1.553
    },
    {
      "date": "1963-12-01",
      "value": 1.669
    },
    {
      "date": "1964-01-01",
      "value": 1.617
    },
    {
      "date": "1964-02-01",
      "value": 1.694
    },
    {
      "date": "1964-03-01",
      "value": 1.729
    },
    {
      "date": "1964-04-01",
      "value": 1.697
    },
    {
      "date": "1964-05-01",
      "value": 1.597
    },
    {
      "date": "1964-06-01",
      "value": 1.498
    },
    {
      "date": "1964-07-01",
      "value": 1.508
    },
    {
      "date": "1964-08-01",
      "value": 1.549
    },
    {
      "date": "1964-09-01",
      "value": 1.408
    },
    {
      "date": "1964-10-01",
      "value": 1.225
    },
    {
      "date": "1964-11-01",
      "value": 1.278
    },
    {
      "date": "1964-12-01",
      "value": 1.276
    },
    {
      "date": "1965-01-01",
      "value": 1.274
    },
    {
      "date": "1965-02-01",
      "value": 1.2
    },
    {
      "date": "1965-03-01",
      "value": 1.163
    },
    {
      "date": "1965-04-01",
      "value": 1.192
    },
    {
      "date": "1965-05-01",
      "value": 1.292
    },
    {
      "date": "1965-06-01",
      "value": 1.196
    },
    {
      "date": "1965-07-01",
      "value": 1.195
    },
    {
      "date": "1965-08-01",
      "value": 1.253
    },
    {
      "date": "1965-09-01",
      "value": 1.329
    },
    {
      "date": "1965-10-01",
      "value": 1.252
    },
    {
      "date": "1965-11-01",
      "value": 1.297
    },
    {
      "date": "1965-12-01",
      "value": 1.461
    },
    {
      "date": "1966-01-01",
      "value": 1.353
    },
    {
      "date": "1966-02-01",
      "value": 1.481
    },
    {
      "date": "1966-03-01",
      "value": 1.551
    },
    {
      "date": "1966-04-01",
      "value": 1.796
    },
    {
      "date": "1966-05-01",
      "value": 1.881
    },
    {
      "date": "1966-06-01",
      "value": 2.234
    },
    {
      "date": "1966-07-01",
      "value": 2.432
    },
    {
      "date": "1966-08-01",
      "value": 2.427
    },
    {
      "date": "1966-09-01",
      "value": 2.624
    },
    {
      "date": "1966-10-01",
      "value": 2.994
    },
    {
      "date": "1966-11-01",
      "value": 3.058
    },
    {
      "date": "1966-12-01",
      "value": 3.061
    },
    {
      "date": "1967-01-01",
      "value": 3.124
    },
    {
      "date": "1967-02-01",
      "value": 3.058
    },
    {
      "date": "1967-03-01",
      "value": 3.083
    },
    {
      "date": "1967-04-01",
      "value": 2.997
    },
    {
      "date": "1967-05-01",
      "value": 2.948
    },
    {
      "date": "1967-06-01",
      "value": 2.876
    },
    {
      "date": "1967-07-01",
      "value": 2.925
    },
    {
      "date": "1967-08-01",
      "value": 3.051
    },
    {
      "date": "1967-09-01",
      "value": 3.099
    },
    {
      "date": "1967-10-01",
      "value": 3.145
    },
    {
      "date": "1967-11-01",
      "value": 3.217
    },
    {
      "date": "1967-12-01",
      "value": 3.156
    },
    {
      "date": "1968-01-01",
      "value": 3.521
    },
    {
      "date": "1968-02-01",
      "value": 3.78
    },
    {
      "date": "1968-03-01",
      "value": 4.033
    },
    {
      "date": "1968-04-01",
      "value": 4.129
    },
    {
      "date": "1968-05-01",
      "value": 4.293
    },
    {
      "date": "1968-06-01",
      "value": 4.439
    },
    {
      "date": "1968-07-01",
      "value": 4.429
    },
    {
      "date": "1968-08-01",
      "value": 4.516
    },
    {
      "date": "1968-09-01",
      "value": 4.566
    },
    {
      "date": "1968-10-01",
      "value": 4.605
    },
    {
      "date": "1968-11-01",
      "value": 4.667
    },
    {
      "date": "1968-12-01",
      "value": 4.721
    },
    {
      "date": "1969-01-01",
      "value": 4.651
    },
    {
      "date": "1969-02-01",
      "value": 4.561
    },
    {
      "date": "1969-03-01",
      "value": 4.635
    },
    {
      "date": "1969-04-01",
      "value": 4.65
    },
    {
      "date": "1969-05-01",
      "value": 4.675
    },
    {
      "date": "1969-06-01",
      "value": 4.625
    },
    {
      "date": "1969-07-01",
      "value": 4.764
    },
    {
      "date": "1969-08-01",
      "value": 4.65
    },
    {
      "date": "1969-09-01",
      "value": 4.647
    },
    {
      "date": "1969-10-01",
      "value": 4.671
    },
    {
      "date": "1969-11-01",
      "value": 4.674
    },
    {
      "date": "1969-12-01",
      "value": 4.749
    }
  ],
  "latest_yoy_date": "1969-12-01",
  "latest_yoy_value": 4.749,
  "mom_observations": [
    {
      "date": "1960-01-01",
      "value": 0.025
    },
    {
      "date": "1960-02-01",
      "value": 0.19
    },
    {
      "date": "1960-03-01",
      "value": 0.006
    },
    {
      "date": "1960-04-01",
      "value": 0.183
    },
    {
      "date": "1960-05-01",
      "value": 0.164
    },
    {
      "date": "1960-06-01",
      "value": 0.057
    },
    {
      "date": "1960-07-01",
      "value": 0.176
    },
    {
      "date": "1960-08-01",
      "value": 0.144
    },
    {
      "date": "1960-09-01",
      "value": 0.081
    },
    {
      "date": "1960-10-01",
      "value": 0.056
    },
    {
      "date": "1960-11-01",
      "value": 0.269
    },
    {
      "date": "1960-12-01",
      "value": -0.031
    },
    {
      "date": "1961-01-01",
      "value": 0.025
    },
    {
      "date": "1961-02-01",
      "value": 0.1
    },
    {
      "date": "1961-03-01",
      "value": 0.031
    },
    {
      "date": "1961-04-01",
      "value": 0.137
    },
    {
      "date": "1961-05-01",
      "value": 0.131
    },
    {
      "date": "1961-06-01",
      "value": 0.149
    },
    {
      "date": "1961-07-01",
      "value": 0.155
    },
    {
      "date": "1961-08-01",
      "value": 0.105
    },
    {
      "date": "1961-09-01",
      "value": 0.198
    },
    {
      "date": "1961-10-01",
      "value": 0.031
    },
    {
      "date": "1961-11-01",
      "value": 0.019
    },
    {
      "date": "1961-12-01",
      "value": 0.086
    },
    {
      "date": "1962-01-01",
      "value": 0.117
    },
    {
      "date": "1962-02-01",
      "value": 0.166
    },
    {
      "date": "1962-03-01",
      "value": 0.234
    },
    {
      "date": "1962-04-01",
      "value": 0.018
    },
    {
      "date": "1962-05-01",
      "value": 0.141
    },
    {
      "date": "1962-06-01",
      "value": 0.184
    },
    {
      "date": "1962-07-01",
      "value": 0.086
    },
    {
      "date": "1962-08-01",
      "value": 0.012
    },
    {
      "date": "1962-09-01",
      "value": 0.195
    },
    {
      "date": "1962-10-01",
      "value": -0.006
    },
    {
      "date": "1962-11-01",
      "value": 0.073
    },
    {
      "date": "1962-12-01",
      "value": 0.03
    },
    {
      "date": "1963-01-01",
      "value": 0.189
    },
    {
      "date": "1963-02-01",
      "value": 0.115
    },
    {
      "date": "1963-03-01",
      "value": 0.061
    },
    {
      "date": "1963-04-01",
      "value": 0.121
    },
    {
      "date": "1963-05-01",
      "value": 0.182
    },
    {
      "date": "1963-06-01",
      "value": 0.169
    },
    {
      "date": "1963-07-01",
      "value": 0.091
    },
    {
      "date": "1963-08-01",
      "value": 0.091
    },
    {
      "date": "1963-09-01",
      "value": 0.181
    },
    {
      "date": "1963-10-01",
      "value": 0.223
    },
    {
      "date": "1963-11-01",
      "value": 0.09
    },
    {
      "date": "1963-12-01",
      "value": 0.144
    },
    {
      "date": "1964-01-01",
      "value": 0.138
    },
    {
      "date": "1964-02-01",
      "value": 0.191
    },
    {
      "date": "1964-03-01",
      "value": 0.096
    },
    {
      "date": "1964-04-01",
      "value": 0.089
    },
    {
      "date": "1964-05-01",
      "value": 0.083
    },
    {
      "date": "1964-06-01",
      "value": 0.071
    },
    {
      "date": "1964-07-01",
      "value": 0.101
    },
    {
      "date": "1964-08-01",
      "value": 0.131
    },
    {
      "date": "1964-09-01",
      "value": 0.042
    },
    {
      "date": "1964-10-01",
      "value": 0.042
    },
    {
      "date": "1964-11-01",
      "value": 0.142
    },
    {
      "date": "1964-12-01",
      "value": 0.142
    },
    {
      "date": "1965-01-01",
      "value": 0.136
    },
    {
      "date": "1965-02-01",
      "value": 0.118
    },
    {
      "date": "1965-03-01",
      "value": 0.059
    },
    {
      "date": "1965-04-01",
      "value": 0.118
    },
    {
      "date": "1965-05-01",
      "value": 0.183
    },
    {
      "date": "1965-06-01",
      "value": -0.024
    },
    {
      "date": "1965-07-01",
      "value": 0.1
    },
    {
      "date": "1965-08-01",
      "value": 0.188
    },
    {
      "date": "1965-09-01",
      "value": 0.117
    },
    {
      "date": "1965-10-01",
      "value": -0.035
    },
    {
      "date": "1965-11-01",
      "value": 0.187
    },
    {
      "date": "1965-12-01",
      "value": 0.304
    },
    {
      "date": "1966-01-01",
      "value": 0.029
    },
    {
      "date": "1966-02-01",
      "value": 0.245
    },
    {
      "date": "1966-03-01",
      "value": 0.128
    },
    {
      "date": "1966-04-01",
      "value": 0.36
    },
    {
      "date": "1966-05-01",
      "value": 0.266
    },
    {
      "date": "1966-06-01",
      "value": 0.323
    },
    {
      "date": "1966-07-01",
      "value": 0.293
    },
    {
      "date": "1966-08-01",
      "value": 0.184
    },
    {
      "date": "1966-09-01",
      "value": 0.309
    },
    {
      "date": "1966-10-01",
      "value": 0.325
    },
    {
      "date": "1966-11-01",
      "value": 0.25
    },
    {
      "date": "1966-12-01",
      "value": 0.306
    },
    {
      "date": "1967-01-01",
      "value": 0.091
    },
    {
      "date": "1967-02-01",
      "value": 0.181
    },
    {
      "date": "1967-03-01",
      "value": 0.152
    },
    {
      "date": "1967-04-01",
      "value": 0.276
    },
    {
      "date": "1967-05-01",
      "value": 0.219
    },
    {
      "date": "1967-06-01",
      "value": 0.252
    },
    {
      "date": "1967-07-01",
      "value": 0.341
    },
    {
      "date": "1967-08-01",
      "value": 0.306
    },
    {
      "date": "1967-09-01",
      "value": 0.355
    },
    {
      "date": "1967-10-01",
      "value": 0.371
    },
    {
      "date": "1967-11-01",
      "value": 0.32
    },
    {
      "date": "1967-12-01",
      "value": 0.247
    },
    {
      "date": "1968-01-01",
      "value": 0.444
    },
    {
      "date": "1968-02-01",
      "value": 0.431
    },
    {
      "date": "1968-03-01",
      "value": 0.397
    },
    {
      "date": "1968-04-01",
      "value": 0.368
    },
    {
      "date": "1968-05-01",
      "value": 0.378
    },
    {
      "date": "1968-06-01",
      "value": 0.392
    },
    {
      "date": "1968-07-01",
      "value": 0.332
    },
    {
      "date": "1968-08-01",
      "value": 0.389
    },
    {
      "date": "1968-09-01",
      "value": 0.404
    },
    {
      "date": "1968-10-01",
      "value": 0.408
    },
    {
      "date": "1968-11-01",
      "value": 0.38
    },
    {
      "date": "1968-12-01",
      "value": 0.299
    },
    {
      "date": "1969-01-01",
      "value": 0.377
    },
    {
      "date": "1969-02-01",
      "value": 0.344
    },
    {
      "date": "1969-03-01",
      "value": 0.468
    },
    {
      "date": "1969-04-01",
      "value": 0.383
    },
    {
      "date": "1969-05-01",
      "value": 0.402
    },
    {
      "date": "1969-06-01",
      "value": 0.344
    },
    {
      "date": "1969-07-01",
      "value": 0.466
    },
    {
      "date": "1969-08-01",
      "value": 0.28
    },
    {
      "date": "1969-09-01",
      "value": 0.401
    },
    {
      "date": "1969-10-01",
      "value": 0.43
    },
    {
      "date": "1969-11-01",
      "value": 0.383
    },
    {
      "date": "1969-12-01",
      "value": 0.371
    }
  ],
  "latest_mom_date": "1969-12-01",
  "latest_mom_value": 0.371,
  "observations": [
    {
      "date": "1960-01-01",
      "value": 2.071
    },
    {
      "date": "1960-02-01",
      "value": 2.185
    },
    {
      "date": "1960-03-01",
      "value": 2.073
    },
    {
      "date": "1960-04-01",
      "value": 2.004
    },
    {
      "date": "1960-05-01",
      "value": 2.046
    },
    {
      "date": "1960-06-01",
      "value": 1.804
    },
    {
      "date": "1960-07-01",
      "value": 1.742
    },
    {
      "date": "1960-08-01",
      "value": 1.726
    },
    {
      "date": "1960-09-01",
      "value": 1.544
    },
    {
      "date": "1960-10-01",
      "value": 1.427
    },
    {
      "date": "1960-11-01",
      "value": 1.513
    },
    {
      "date": "1960-12-01",
      "value": 1.328
    },
    {
      "date": "1961-01-01",
      "value": 1.327
    },
    {
      "date": "1961-02-01",
      "value": 1.236
    },
    {
      "date": "1961-03-01",
      "value": 1.262
    },
    {
      "date": "1961-04-01",
      "value": 1.215
    },
    {
      "date": "1961-05-01",
      "value": 1.182
    },
    {
      "date": "1961-06-01",
      "value": 1.275
    },
    {
      "date": "1961-07-01",
      "value": 1.254
    },
    {
      "date": "1961-08-01",
      "value": 1.215
    },
    {
      "date": "1961-09-01",
      "value": 1.333
    },
    {
      "date": "1961-10-01",
      "value": 1.307
    },
    {
      "date": "1961-11-01",
      "value": 1.054
    },
    {
      "date": "1961-12-01",
      "value": 1.173
    },
    {
      "date": "1962-01-01",
      "value": 1.266
    },
    {
      "date": "1962-02-01",
      "value": 1.333
    },
    {
      "date": "1962-03-01",
      "value": 1.539
    },
    {
      "date": "1962-04-01",
      "value": 1.418
    },
    {
      "date": "1962-05-01",
      "value": 1.429
    },
    {
      "date": "1962-06-01",
      "value": 1.464
    },
    {
      "date": "1962-07-01",
      "value": 1.394
    },
    {
      "date": "1962-08-01",
      "value": 1.299
    },
    {
      "date": "1962-09-01",
      "value": 1.297
    },
    {
      "date": "1962-10-01",
      "value": 1.259
    },
    {
      "date": "1962-11-01",
      "value": 1.315
    },
    {
      "date": "1962-12-01",
      "value": 1.258
    },
    {
      "date": "1963-01-01",
      "value": 1.33
    },
    {
      "date": "1963-02-01",
      "value": 1.279
    },
    {
      "date": "1963-03-01",
      "value": 1.104
    },
    {
      "date": "1963-04-01",
      "value": 1.208
    },
    {
      "date": "1963-05-01",
      "value": 1.25
    },
    {
      "date": "1963-06-01",
      "value": 1.235
    },
    {
      "date": "1963-07-01",
      "value": 1.24
    },
    {
      "date": "1963-08-01",
      "value": 1.319
    },
    {
      "date": "1963-09-01",
      "value": 1.305
    },
    {
      "date": "1963-10-01",
      "value": 1.536
    },
    {
      "date": "1963-11-01",
      "value": 1.553
    },
    {
      "date": "1963-12-01",
      "value": 1.669
    },
    {
      "date": "1964-01-01",
      "value": 1.617
    },
    {
      "date": "1964-02-01",
      "value": 1.694
    },
    {
      "date": "1964-03-01",
      "value": 1.729
    },
    {
      "date": "1964-04-01",
      "value": 1.697
    },
    {
      "date": "1964-05-01",
      "value": 1.597
    },
    {
      "date": "1964-06-01",
      "value": 1.498
    },
    {
      "date": "1964-07-01",
      "value": 1.508
    },
    {
      "date": "1964-08-01",
      "value": 1.549
    },
    {
      "date": "1964-09-01",
      "value": 1.408
    },
    {
      "date": "1964-10-01",
      "value": 1.225
    },
    {
      "date": "1964-11-01",
      "value": 1.278
    },
    {
      "date": "1964-12-01",
      "value": 1.276
    },
    {
      "date": "1965-01-01",
      "value": 1.274
    },
    {
      "date": "1965-02-01",
      "value": 1.2
    },
    {
      "date": "1965-03-01",
      "value": 1.163
    },
    {
      "date": "1965-04-01",
      "value": 1.192
    },
    {
      "date": "1965-05-01",
      "value": 1.292
    },
    {
      "date": "1965-06-01",
      "value": 1.196
    },
    {
      "date": "1965-07-01",
      "value": 1.195
    },
    {
      "date": "1965-08-01",
      "value": 1.253
    },
    {
      "date": "1965-09-01",
      "value": 1.329
    },
    {
      "date": "1965-10-01",
      "value": 1.252
    },
    {
      "date": "1965-11-01",
      "value": 1.297
    },
    {
      "date": "1965-12-01",
      "value": 1.461
    },
    {
      "date": "1966-01-01",
      "value": 1.353
    },
    {
      "date": "1966-02-01",
      "value": 1.481
    },
    {
      "date": "1966-03-01",
      "value": 1.551
    },
    {
      "date": "1966-04-01",
      "value": 1.796
    },
    {
      "date": "1966-05-01",
      "value": 1.881
    },
    {
      "date": "1966-06-01",
      "value": 2.234
    },
    {
      "date": "1966-07-01",
      "value": 2.432
    },
    {
      "date": "1966-08-01",
      "value": 2.427
    },
    {
      "date": "1966-09-01",
      "value": 2.624
    },
    {
      "date": "1966-10-01",
      "value": 2.994
    },
    {
      "date": "1966-11-01",
      "value": 3.058
    },
    {
      "date": "1966-12-01",
      "value": 3.061
    },
    {
      "date": "1967-01-01",
      "value": 3.124
    },
    {
      "date": "1967-02-01",
      "value": 3.058
    },
    {
      "date": "1967-03-01",
      "value": 3.083
    },
    {
      "date": "1967-04-01",
      "value": 2.997
    },
    {
      "date": "1967-05-01",
      "value": 2.948
    },
    {
      "date": "1967-06-01",
      "value": 2.876
    },
    {
      "date": "1967-07-01",
      "value": 2.925
    },
    {
      "date": "1967-08-01",
      "value": 3.051
    },
    {
      "date": "1967-09-01",
      "value": 3.099
    },
    {
      "date": "1967-10-01",
      "value": 3.145
    },
    {
      "date": "1967-11-01",
      "value": 3.217
    },
    {
      "date": "1967-12-01",
      "value": 3.156
    },
    {
      "date": "1968-01-01",
      "value": 3.521
    },
    {
      "date": "1968-02-01",
      "value": 3.78
    },
    {
      "date": "1968-03-01",
      "value": 4.033
    },
    {
      "date": "1968-04-01",
      "value": 4.129
    },
    {
      "date": "1968-05-01",
      "value": 4.293
    },
    {
      "date": "1968-06-01",
      "value": 4.439
    },
    {
      "date": "1968-07-01",
      "value": 4.429
    },
    {
      "date": "1968-08-01",
      "value": 4.516
    },
    {
      "date": "1968-09-01",
      "value": 4.566
    },
    {
      "date": "1968-10-01",
      "value": 4.605
    },
    {
      "date": "1968-11-01",
      "value": 4.667
    },
    {
      "date": "1968-12-01",
      "value": 4.721
    },
    {
      "date": "1969-01-01",
      "value": 4.651
    },
    {
      "date": "1969-02-01",
      "value": 4.561
    },
    {
      "date": "1969-03-01",
      "value": 4.635
    },
    {
      "date": "1969-04-01",
      "value": 4.65
    },
    {
      "date": "1969-05-01",
      "value": 4.675
    },
    {
      "date": "1969-06-01",
      "value": 4.625
    },
    {
      "date": "1969-07-01",
      "value": 4.764
    },
    {
      "date": "1969-08-01",
      "value": 4.65
    },
    {
      "date": "1969-09-01",
      "value": 4.647
    },
    {
      "date": "1969-10-01",
      "value": 4.671
    },
    {
      "date": "1969-11-01",
      "value": 4.674
    },
    {
      "date": "1969-12-01",
      "value": 4.749
    }
  ],
  "latest_date": "1969-12-01",
  "latest_value": 4.749,
  "fetched_at": "2026-05-26T09:08:29.662982Z",
  "count": 132
}